range_sum_lib/__init__.py
range_sum_lib/__main__.py
rangenumberssumlib-0.1.0.dist-info/licenses/LICENSE
rangenumberssumlib-0.1.0.dist-info/METADATA
rangenumberssumlib-0.1.0.dist-info/WHEEL
rangenumberssumlib-0.1.0.dist-info/entry_points.txt
rangenumberssumlib-0.1.0.dist-info/top_level.txt
rangenumberssumlib-0.1.0.dist-info/RECORD
