Metadata-Version: 2.4
Name: RangeNumbersSumLib
Version: 0.1.0
Summary: Calculate sum from a to b
Author-email: Suhail Nabil Alansi <suhail09t12@gmail.com>
License: MIT License
Requires-Python: >=3.7
License-File: LICENSE
Dynamic: license-file
